LICENSE.md
README.md
setup.py
DidemTaha/__init__.py
DidemTaha.egg-info/PKG-INFO
DidemTaha.egg-info/SOURCES.txt
DidemTaha.egg-info/dependency_links.txt
DidemTaha.egg-info/top_level.txt
DidemTaha/data_prep/__init__.py
DidemTaha/data_prep/data_prep.py
DidemTaha/eda/__init__.py
DidemTaha/eda/eda.py